{
  "type" : "CIMLayerDocument",
  "version" : "2.9.0",
  "build" : 32739,
  "layers" : [
    "CIMPATH=salt/group.xml"
  ],
  "layerDefinitions" : [],
  "binaryReferences" : [],
  "elevationSurfaces" : [
    {
      "type" : "CIMMapElevationSurface",
      "elevationMode" : "BaseGlobeSurface",
      "name" : "Ground",
      "verticalExaggeration" : 1,
      "mapElevationID" : "{752ADD4F-A4BC-44F1-8B73-D03138DD2020}",
      "color" : {
        "type" : "CIMRGBColor",
        "values" : [
          255,
          255,
          255,
          100
        ]
      },
      "surfaceTINShadingMode" : "Smooth",
      "visibility" : true,
      "expanded" : true
    }
  ],
  "rGBColorProfile" : "sRGB IEC61966-2-1 noBPC",
  "cMYKColorProfile" : "U.S. Web Coated (SWOP) v2"
}